feor/afk/__init__.py
feor/afk/app.py
feor/afk/views.py
feor/afk/templates/AFK.Script.Txt
feor/afk/templates/AFK.xml
pyplanet_afk_spec-0.7.2.dist-info/METADATA
pyplanet_afk_spec-0.7.2.dist-info/WHEEL
pyplanet_afk_spec-0.7.2.dist-info/licenses/LICENSE
pyplanet_afk_spec-0.7.2.dist-info/RECORD
