Metadata-Version: 2.3
Name: pyplanet-afk_spec
Version: 0.7.2
Summary: A Pyplanet server controller plugin to automatically move players to spectator mode if they are AFK.
Project-URL: Homepage, https://github.com/feored/pyplanet-afk_spec
Project-URL: Bug Tracker, https://github.com/feored/pyplanet-afk_spec/issues
Author: feor
License-File: LICENSE
Classifier: License :: OSI Approved :: MIT License
Classifier: Programming Language :: Python :: 3
Classifier: Programming Language :: Python :: 3 :: Only
Classifier: Topic :: Games/Entertainment
Requires-Python: >=3.7
